{"version":{"fullVersion":"2.4.9","major":"2","minor":"4","patch":"9"},"meta":{"flags":["experimentalData"]},"collections":[{"name":"home","label":"Главная","path":"content/home","format":"json","ui":{},"templates":[{"name":"homeHero","label":"Hero (главный экран)","fields":[{"type":"string","name":"tagline","label":"Тэглайн","namespace":["home","homeHero","tagline"],"searchable":true,"uid":false},{"type":"string","name":"heading","label":"Заголовок (H1)","namespace":["home","homeHero","heading"],"searchable":true,"uid":false},{"type":"string","name":"description","label":"Описание","ui":{"component":"textarea"},"namespace":["home","homeHero","description"],"searchable":true,"uid":false},{"type":"string","name":"pricing","label":"Цена (строка)","namespace":["home","homeHero","pricing"],"searchable":true,"uid":false},{"type":"object","name":"cta","label":"Кнопки","fields":[{"type":"string","name":"consultation","label":"Получить консультацию","namespace":["home","homeHero","cta","consultation"]},{"type":"string","name":"cases","label":"Посмотреть кейсы","namespace":["home","homeHero","cta","cases"]}],"namespace":["home","homeHero","cta"],"searchable":true,"uid":false},{"type":"object","name":"stats","label":"Статистика","list":true,"fields":[{"type":"string","name":"value","label":"Значение","namespace":["home","homeHero","stats","value"]},{"type":"string","name":"label","label":"Подпись","namespace":["home","homeHero","stats","label"]}],"namespace":["home","homeHero","stats"],"searchable":true,"uid":false}],"namespace":["home","homeHero"]},{"name":"homeAbout","label":"About (О бренде)","fields":[{"type":"string","name":"eyebrow","label":"Айброу","namespace":["home","homeAbout","eyebrow"],"searchable":true,"uid":false},{"type":"string","name":"headingBefore","label":"Заголовок (до акцента)","namespace":["home","homeAbout","headingBefore"],"searchable":true,"uid":false},{"type":"string","name":"headingAccent","label":"Заголовок (акцент)","namespace":["home","homeAbout","headingAccent"],"searchable":true,"uid":false},{"type":"string","name":"headingAfter","label":"Заголовок (после акцента)","namespace":["home","homeAbout","headingAfter"],"searchable":true,"uid":false},{"type":"string","name":"body","label":"Текст","ui":{"component":"textarea"},"namespace":["home","homeAbout","body"],"searchable":true,"uid":false},{"type":"object","name":"aboutLinks","label":"Ссылки","fields":[{"type":"string","name":"about","label":"О бренде","namespace":["home","homeAbout","aboutLinks","about"]},{"type":"string","name":"collection","label":"Коллекции","namespace":["home","homeAbout","aboutLinks","collection"]}],"namespace":["home","homeAbout","aboutLinks"],"searchable":true,"uid":false}],"namespace":["home","homeAbout"]},{"name":"homeFranchise","label":"Franchise (Франшиза на главной)","fields":[{"type":"string","name":"eyebrow","label":"Айброу","namespace":["home","homeFranchise","eyebrow"],"searchable":true,"uid":false},{"type":"string","name":"heading","label":"Заголовок","namespace":["home","homeFranchise","heading"],"searchable":true,"uid":false},{"type":"string","name":"desc","label":"Описание","namespace":["home","homeFranchise","desc"],"searchable":true,"uid":false},{"type":"string","name":"ctaButton","label":"Кнопка CTA","namespace":["home","homeFranchise","ctaButton"],"searchable":true,"uid":false},{"type":"object","name":"franchiseLabels","label":"Подписи к карточкам","fields":[{"type":"string","name":"investment","label":"Инвестиции","namespace":["home","homeFranchise","franchiseLabels","investment"]},{"type":"string","name":"profitMonth","label":"Прибыль / мес","namespace":["home","homeFranchise","franchiseLabels","profitMonth"]}],"namespace":["home","homeFranchise","franchiseLabels"],"searchable":true,"uid":false},{"type":"object","name":"franchiseLinks","label":"Ссылки под CTA","fields":[{"type":"string","name":"allConditions","label":"Все условия франшизы","namespace":["home","homeFranchise","franchiseLinks","allConditions"]},{"type":"string","name":"example","label":"Пример магазина","namespace":["home","homeFranchise","franchiseLinks","example"]}],"namespace":["home","homeFranchise","franchiseLinks"],"searchable":true,"uid":false},{"type":"string","name":"disclaimer","label":"Дисклеймер","ui":{"component":"textarea"},"namespace":["home","homeFranchise","disclaimer"],"searchable":true,"uid":false}],"namespace":["home","homeFranchise"]},{"name":"homeMarketBlock","label":"MarketBlock (Почему сейчас)","fields":[{"type":"string","name":"eyebrow","label":"Айброу","namespace":["home","homeMarketBlock","eyebrow"],"searchable":true,"uid":false},{"type":"string","name":"headingBefore","label":"Заголовок (до акцента)","namespace":["home","homeMarketBlock","headingBefore"],"searchable":true,"uid":false},{"type":"string","name":"headingAccent","label":"Заголовок (акцент)","namespace":["home","homeMarketBlock","headingAccent"],"searchable":true,"uid":false},{"type":"string","name":"desc","label":"Описание","namespace":["home","homeMarketBlock","desc"],"searchable":true,"uid":false},{"type":"string","name":"reasons","label":"Причины","list":true,"ui":{"component":"textarea"},"namespace":["home","homeMarketBlock","reasons"],"searchable":true,"uid":false}],"namespace":["home","homeMarketBlock"]},{"name":"homeTrustModel","label":"TrustModel (Как устроена модель)","fields":[{"type":"string","name":"eyebrow","label":"Айброу","namespace":["home","homeTrustModel","eyebrow"],"searchable":true,"uid":false},{"type":"string","name":"headingBefore","label":"Заголовок (до акцента)","namespace":["home","homeTrustModel","headingBefore"],"searchable":true,"uid":false},{"type":"string","name":"headingAccent","label":"Заголовок (акцент)","namespace":["home","homeTrustModel","headingAccent"],"searchable":true,"uid":false},{"type":"string","name":"desc","label":"Описание","namespace":["home","homeTrustModel","desc"],"searchable":true,"uid":false}],"namespace":["home","homeTrustModel"]},{"name":"homeRoadmap","label":"Roadmap (Как открыть)","fields":[{"type":"string","name":"eyebrow","label":"Айброу","namespace":["home","homeRoadmap","eyebrow"],"searchable":true,"uid":false},{"type":"string","name":"headingBefore","label":"Заголовок (до акцента)","namespace":["home","homeRoadmap","headingBefore"],"searchable":true,"uid":false},{"type":"string","name":"headingAccent","label":"Заголовок (акцент)","namespace":["home","homeRoadmap","headingAccent"],"searchable":true,"uid":false},{"type":"string","name":"desc","label":"Описание","namespace":["home","homeRoadmap","desc"],"searchable":true,"uid":false}],"namespace":["home","homeRoadmap"]},{"name":"homeCaseStudies","label":"CaseStudies (Кейсы)","fields":[{"type":"string","name":"eyebrow","label":"Айброу","namespace":["home","homeCaseStudies","eyebrow"],"searchable":true,"uid":false},{"type":"string","name":"headingBefore","label":"Заголовок (до акцента)","namespace":["home","homeCaseStudies","headingBefore"],"searchable":true,"uid":false},{"type":"string","name":"headingAccent","label":"Заголовок (акцент)","namespace":["home","homeCaseStudies","headingAccent"],"searchable":true,"uid":false},{"type":"string","name":"desc","label":"Описание","namespace":["home","homeCaseStudies","desc"],"searchable":true,"uid":false},{"type":"object","name":"caseLabels","label":"Подписи","fields":[{"type":"string","name":"payback","label":"Окупаемость","namespace":["home","homeCaseStudies","caseLabels","payback"]},{"type":"string","name":"profitMonth","label":"Прибыль / мес","namespace":["home","homeCaseStudies","caseLabels","profitMonth"]},{"type":"string","name":"investment","label":"Инвестиции","namespace":["home","homeCaseStudies","caseLabels","investment"]},{"type":"string","name":"video","label":"Видео","namespace":["home","homeCaseStudies","caseLabels","video"]},{"type":"string","name":"photo","label":"Фото","namespace":["home","homeCaseStudies","caseLabels","photo"]}],"namespace":["home","homeCaseStudies","caseLabels"],"searchable":true,"uid":false},{"type":"string","name":"openedPrefix","label":"Префикс даты открытия","namespace":["home","homeCaseStudies","openedPrefix"],"searchable":true,"uid":false},{"type":"string","name":"openedSuffix","label":"Суффикс даты открытия","namespace":["home","homeCaseStudies","openedSuffix"],"searchable":true,"uid":false}],"namespace":["home","homeCaseStudies"]},{"name":"homeFaq","label":"FAQ (Часто спрашивают)","fields":[{"type":"string","name":"eyebrow","label":"Айброу","namespace":["home","homeFaq","eyebrow"],"searchable":true,"uid":false},{"type":"string","name":"headingBefore","label":"Заголовок (до акцента)","namespace":["home","homeFaq","headingBefore"],"searchable":true,"uid":false},{"type":"string","name":"headingAccent","label":"Заголовок (акцент)","namespace":["home","homeFaq","headingAccent"],"searchable":true,"uid":false},{"type":"string","name":"desc","label":"Описание","namespace":["home","homeFaq","desc"],"searchable":true,"uid":false}],"namespace":["home","homeFaq"]},{"name":"homeContacts","label":"Contacts (Контакты)","fields":[{"type":"string","name":"eyebrow","label":"Айброу","namespace":["home","homeContacts","eyebrow"],"searchable":true,"uid":false},{"type":"string","name":"heading","label":"Заголовок","namespace":["home","homeContacts","heading"],"searchable":true,"uid":false},{"type":"string","name":"desc","label":"Описание","namespace":["home","homeContacts","desc"],"searchable":true,"uid":false},{"type":"object","name":"form","label":"Форма","fields":[{"type":"string","name":"name","label":"Имя (label)","namespace":["home","homeContacts","form","name"]},{"type":"string","name":"namePlaceholder","label":"Имя (placeholder)","namespace":["home","homeContacts","form","namePlaceholder"]},{"type":"string","name":"phone","label":"Телефон (label)","namespace":["home","homeContacts","form","phone"]},{"type":"string","name":"phonePlaceholder","label":"Телефон (placeholder)","namespace":["home","homeContacts","form","phonePlaceholder"]},{"type":"string","name":"format","label":"Формат (label)","namespace":["home","homeContacts","form","format"]},{"type":"string","name":"formatPlaceholder","label":"Формат (placeholder)","namespace":["home","homeContacts","form","formatPlaceholder"]},{"type":"string","name":"message","label":"Сообщение (label)","namespace":["home","homeContacts","form","message"]},{"type":"string","name":"messagePlaceholder","label":"Сообщение (placeholder)","namespace":["home","homeContacts","form","messagePlaceholder"]},{"type":"string","name":"submit","label":"Кнопка отправки","namespace":["home","homeContacts","form","submit"]},{"type":"string","name":"submitting","label":"Отправка...","namespace":["home","homeContacts","form","submitting"]},{"type":"string","name":"submitted","label":"Отправлено","namespace":["home","homeContacts","form","submitted"]},{"type":"string","name":"success","label":"Успех","namespace":["home","homeContacts","form","success"]},{"type":"string","name":"error","label":"Ошибка","namespace":["home","homeContacts","form","error"]},{"type":"string","name":"telegram","label":"Telegram (текст ссылки)","namespace":["home","homeContacts","form","telegram"]},{"type":"string","name":"or","label":"или","namespace":["home","homeContacts","form","or"]},{"type":"string","name":"mail","label":"почта (текст ссылки)","namespace":["home","homeContacts","form","mail"]},{"type":"string","name":"leadQueueFallback","label":"Фолбэк сообщения","namespace":["home","homeContacts","form","leadQueueFallback"]}],"namespace":["home","homeContacts","form"],"searchable":true,"uid":false},{"type":"object","name":"company","label":"Компания","fields":[{"type":"string","name":"name","label":"Название","namespace":["home","homeContacts","company","name"]},{"type":"string","name":"inn","label":"ИНН","namespace":["home","homeContacts","company","inn"]},{"type":"string","name":"address","label":"Адрес","namespace":["home","homeContacts","company","address"]}],"namespace":["home","homeContacts","company"],"searchable":true,"uid":false},{"type":"object","name":"sections","label":"Заголовки секций","fields":[{"type":"string","name":"details","label":"Реквизиты","namespace":["home","homeContacts","sections","details"]},{"type":"string","name":"contacts","label":"Контакты","namespace":["home","homeContacts","sections","contacts"]},{"type":"string","name":"socials","label":"Социальные сети","namespace":["home","homeContacts","sections","socials"]}],"namespace":["home","homeContacts","sections"],"searchable":true,"uid":false},{"type":"string","name":"privacy","label":"Privacy text","ui":{"component":"textarea"},"namespace":["home","homeContacts","privacy"],"searchable":true,"uid":false}],"namespace":["home","homeContacts"]},{"name":"homeStores","label":"Stores (Партнёрская сеть)","fields":[{"type":"string","name":"eyebrow","label":"Айброу","namespace":["home","homeStores","eyebrow"],"searchable":true,"uid":false},{"type":"string","name":"heading","label":"Заголовок","namespace":["home","homeStores","heading"],"searchable":true,"uid":false},{"type":"string","name":"desc","label":"Описание","namespace":["home","homeStores","desc"],"searchable":true,"uid":false},{"type":"object","name":"ghost","label":"Ghost marker","fields":[{"type":"string","name":"label","label":"Метка","namespace":["home","homeStores","ghost","label"]},{"type":"string","name":"tooltip","label":"Тултип","namespace":["home","homeStores","ghost","tooltip"]},{"type":"string","name":"sidebarYourCity","label":"Ваш город","namespace":["home","homeStores","ghost","sidebarYourCity"]},{"type":"string","name":"sidebarCTA","label":"CTA в сайдбаре","namespace":["home","homeStores","ghost","sidebarCTA"]},{"type":"string","name":"sidebarSubtext","label":"Подтекст","namespace":["home","homeStores","ghost","sidebarSubtext"]}],"namespace":["home","homeStores","ghost"],"searchable":true,"uid":false}],"namespace":["home","homeStores"]},{"name":"homeKpRating","label":"KpRating (Рейтинг КП)","fields":[{"type":"string","name":"eyebrow","label":"Айброу","namespace":["home","homeKpRating","eyebrow"],"searchable":true,"uid":false},{"type":"string","name":"headingAccent","label":"Заголовок (акцент)","namespace":["home","homeKpRating","headingAccent"],"searchable":true,"uid":false},{"type":"string","name":"headingAfter","label":"Заголовок (после акцента)","namespace":["home","homeKpRating","headingAfter"],"searchable":true,"uid":false},{"type":"string","name":"desc","label":"Описание","namespace":["home","homeKpRating","desc"],"searchable":true,"uid":false},{"type":"object","name":"badge","label":"Бейдж","fields":[{"type":"string","name":"rank","label":"Ранг","namespace":["home","homeKpRating","badge","rank"]},{"type":"string","name":"label","label":"Подпись","namespace":["home","homeKpRating","badge","label"]}],"namespace":["home","homeKpRating","badge"],"searchable":true,"uid":false},{"type":"string","name":"body","label":"Текст","ui":{"component":"textarea"},"namespace":["home","homeKpRating","body"],"searchable":true,"uid":false},{"type":"string","name":"ctaLink","label":"Текст ссылки","namespace":["home","homeKpRating","ctaLink"],"searchable":true,"uid":false},{"type":"string","name":"source","label":"Источник","namespace":["home","homeKpRating","source"],"searchable":true,"uid":false},{"type":"string","name":"imageAlt","label":"Alt изображения","namespace":["home","homeKpRating","imageAlt"],"searchable":true,"uid":false}],"namespace":["home","homeKpRating"]}],"namespace":["home"]},{"name":"about","label":"О бренде","path":"content/about","format":"json","ui":{},"templates":[{"name":"aboutHero","label":"Hero","fields":[{"type":"string","name":"heroEyebrow","label":"Айброу","namespace":["about","aboutHero","heroEyebrow"],"searchable":true,"uid":false},{"type":"string","name":"heroHeading","label":"Заголовок","ui":{"component":"textarea"},"namespace":["about","aboutHero","heroHeading"],"searchable":true,"uid":false},{"type":"string","name":"heroDesc","label":"Описание","namespace":["about","aboutHero","heroDesc"],"searchable":true,"uid":false}],"namespace":["about","aboutHero"]},{"name":"aboutStats","label":"Статистика","fields":[{"type":"object","name":"stats","label":"Цифры","list":true,"fields":[{"type":"number","name":"num","label":"Число","namespace":["about","aboutStats","stats","num"]},{"type":"string","name":"suffix","label":"Суффикс (+)","namespace":["about","aboutStats","stats","suffix"]},{"type":"string","name":"label","label":"Подпись","namespace":["about","aboutStats","stats","label"]},{"type":"boolean","name":"accent","label":"Акцентный цвет","namespace":["about","aboutStats","stats","accent"]}],"namespace":["about","aboutStats","stats"],"searchable":true,"uid":false}],"namespace":["about","aboutStats"]},{"name":"aboutPhilosophy","label":"Философия","fields":[{"type":"string","name":"philosophyEyebrow","label":"Айброу","namespace":["about","aboutPhilosophy","philosophyEyebrow"],"searchable":true,"uid":false},{"type":"string","name":"philosophyHeading","label":"Заголовок","ui":{"component":"textarea"},"namespace":["about","aboutPhilosophy","philosophyHeading"],"searchable":true,"uid":false},{"type":"string","name":"philosophyBody1","label":"Абзац 1","ui":{"component":"textarea"},"namespace":["about","aboutPhilosophy","philosophyBody1"],"searchable":true,"uid":false},{"type":"string","name":"philosophyBody2","label":"Абзац 2","ui":{"component":"textarea"},"namespace":["about","aboutPhilosophy","philosophyBody2"],"searchable":true,"uid":false}],"namespace":["about","aboutPhilosophy"]},{"name":"aboutAdvantages","label":"Преимущества","fields":[{"type":"string","name":"advantagesEyebrow","label":"Айброу","namespace":["about","aboutAdvantages","advantagesEyebrow"],"searchable":true,"uid":false},{"type":"string","name":"advantagesHeading","label":"Заголовок","ui":{"component":"textarea"},"namespace":["about","aboutAdvantages","advantagesHeading"],"searchable":true,"uid":false},{"type":"object","name":"advantages","label":"Карточки","list":true,"fields":[{"type":"string","name":"title","label":"Заголовок","namespace":["about","aboutAdvantages","advantages","title"]},{"type":"string","name":"desc","label":"Описание","ui":{"component":"textarea"},"namespace":["about","aboutAdvantages","advantages","desc"]}],"namespace":["about","aboutAdvantages","advantages"],"searchable":true,"uid":false}],"namespace":["about","aboutAdvantages"]},{"name":"aboutTimeline","label":"Таймлайн","fields":[{"type":"string","name":"timelineEyebrow","label":"Айброу","namespace":["about","aboutTimeline","timelineEyebrow"],"searchable":true,"uid":false},{"type":"string","name":"timelineHeading","label":"Заголовок","ui":{"component":"textarea"},"namespace":["about","aboutTimeline","timelineHeading"],"searchable":true,"uid":false},{"type":"object","name":"milestones","label":"События","list":true,"fields":[{"type":"string","name":"year","label":"Год","namespace":["about","aboutTimeline","milestones","year"]},{"type":"string","name":"title","label":"Заголовок","namespace":["about","aboutTimeline","milestones","title"]},{"type":"string","name":"desc","label":"Описание","ui":{"component":"textarea"},"namespace":["about","aboutTimeline","milestones","desc"]}],"namespace":["about","aboutTimeline","milestones"],"searchable":true,"uid":false}],"namespace":["about","aboutTimeline"]},{"name":"aboutRepresentative","label":"Представитель","fields":[{"type":"string","name":"repEyebrow","label":"Айброу","namespace":["about","aboutRepresentative","repEyebrow"],"searchable":true,"uid":false},{"type":"string","name":"repHeading","label":"Заголовок","namespace":["about","aboutRepresentative","repHeading"],"searchable":true,"uid":false},{"type":"string","name":"repBody","label":"Текст","ui":{"component":"textarea"},"namespace":["about","aboutRepresentative","repBody"],"searchable":true,"uid":false},{"type":"string","name":"repInn","label":"ИНН","namespace":["about","aboutRepresentative","repInn"],"searchable":true,"uid":false},{"type":"string","name":"repAddress","label":"Адрес","namespace":["about","aboutRepresentative","repAddress"],"searchable":true,"uid":false}],"namespace":["about","aboutRepresentative"]},{"name":"aboutCta","label":"CTA","fields":[{"type":"string","name":"ctaHeading","label":"Заголовок","ui":{"component":"textarea"},"namespace":["about","aboutCta","ctaHeading"],"searchable":true,"uid":false},{"type":"string","name":"ctaButton","label":"Кнопка","namespace":["about","aboutCta","ctaButton"],"searchable":true,"uid":false}],"namespace":["about","aboutCta"]}],"namespace":["about"]},{"name":"franchise","label":"Франшиза","path":"content/franchise","format":"json","ui":{},"templates":[{"name":"franchiseHero","label":"Hero","fields":[{"type":"string","name":"heroEyebrow","label":"Айброу","namespace":["franchise","franchiseHero","heroEyebrow"],"searchable":true,"uid":false},{"type":"string","name":"heroHeading","label":"Заголовок","ui":{"component":"textarea"},"namespace":["franchise","franchiseHero","heroHeading"],"searchable":true,"uid":false},{"type":"string","name":"heroDesc","label":"Описание","ui":{"component":"textarea"},"namespace":["franchise","franchiseHero","heroDesc"],"searchable":true,"uid":false}],"namespace":["franchise","franchiseHero"]},{"name":"franchisePlans","label":"Планы","fields":[{"type":"string","name":"plansEyebrow","label":"Айброу","namespace":["franchise","franchisePlans","plansEyebrow"],"searchable":true,"uid":false},{"type":"string","name":"plansDesc","label":"Описание","namespace":["franchise","franchisePlans","plansDesc"],"searchable":true,"uid":false},{"type":"string","name":"plansHeading","label":"Заголовок","ui":{"component":"textarea"},"namespace":["franchise","franchisePlans","plansHeading"],"searchable":true,"uid":false}],"namespace":["franchise","franchisePlans"]},{"name":"franchiseComparison","label":"Сравнение","fields":[{"type":"string","name":"comparisonEyebrow","label":"Айброу","namespace":["franchise","franchiseComparison","comparisonEyebrow"],"searchable":true,"uid":false},{"type":"string","name":"comparisonHeading","label":"Заголовок","ui":{"component":"textarea"},"namespace":["franchise","franchiseComparison","comparisonHeading"],"searchable":true,"uid":false}],"namespace":["franchise","franchiseComparison"]},{"name":"franchiseFinancial","label":"Финансовая модель","fields":[{"type":"string","name":"financialEyebrow","label":"Айброу","namespace":["franchise","franchiseFinancial","financialEyebrow"],"searchable":true,"uid":false},{"type":"string","name":"financialDesc","label":"Описание","ui":{"component":"textarea"},"namespace":["franchise","franchiseFinancial","financialDesc"],"searchable":true,"uid":false},{"type":"string","name":"financialHeading","label":"Заголовок","ui":{"component":"textarea"},"namespace":["franchise","franchiseFinancial","financialHeading"],"searchable":true,"uid":false},{"type":"object","name":"financialRows","label":"Строки","list":true,"fields":[{"type":"string","name":"label","label":"Название","namespace":["franchise","franchiseFinancial","financialRows","label"]},{"type":"string","name":"value","label":"Значение","namespace":["franchise","franchiseFinancial","financialRows","value"]},{"type":"string","name":"detail","label":"Детали","namespace":["franchise","franchiseFinancial","financialRows","detail"]},{"type":"boolean","name":"accent","label":"Акцент","namespace":["franchise","franchiseFinancial","financialRows","accent"]}],"namespace":["franchise","franchiseFinancial","financialRows"],"searchable":true,"uid":false},{"type":"string","name":"seasonalityNote","label":"Примечание о сезонности","ui":{"component":"textarea"},"namespace":["franchise","franchiseFinancial","seasonalityNote"],"searchable":true,"uid":false}],"namespace":["franchise","franchiseFinancial"]},{"name":"franchiseBenefits","label":"Преимущества","fields":[{"type":"string","name":"benefitsEyebrow","label":"Айброу","namespace":["franchise","franchiseBenefits","benefitsEyebrow"],"searchable":true,"uid":false},{"type":"string","name":"benefitsHeading","label":"Заголовок","ui":{"component":"textarea"},"namespace":["franchise","franchiseBenefits","benefitsHeading"],"searchable":true,"uid":false}],"namespace":["franchise","franchiseBenefits"]},{"name":"franchiseGallery","label":"Галерея","fields":[{"type":"string","name":"galleryEyebrow","label":"Айброу","namespace":["franchise","franchiseGallery","galleryEyebrow"],"searchable":true,"uid":false},{"type":"string","name":"galleryHeading","label":"Заголовок","namespace":["franchise","franchiseGallery","galleryHeading"],"searchable":true,"uid":false}],"namespace":["franchise","franchiseGallery"]},{"name":"franchiseContact","label":"Контакты","fields":[{"type":"string","name":"contactHeading","label":"Заголовок","ui":{"component":"textarea"},"namespace":["franchise","franchiseContact","contactHeading"],"searchable":true,"uid":false},{"type":"string","name":"contactDesc","label":"Описание","namespace":["franchise","franchiseContact","contactDesc"],"searchable":true,"uid":false}],"namespace":["franchise","franchiseContact"]}],"namespace":["franchise"]},{"name":"pageCollections","label":"Коллекции","path":"content/collection","format":"json","ui":{},"templates":[{"name":"collectionHero","label":"Hero","fields":[{"type":"string","name":"heroEyebrow","label":"Айброу","namespace":["pageCollections","collectionHero","heroEyebrow"],"searchable":true,"uid":false},{"type":"string","name":"heroHeading","label":"Заголовок","ui":{"component":"textarea"},"namespace":["pageCollections","collectionHero","heroHeading"],"searchable":true,"uid":false},{"type":"string","name":"heroDesc","label":"Описание","ui":{"component":"textarea"},"namespace":["pageCollections","collectionHero","heroDesc"],"searchable":true,"uid":false}],"namespace":["pageCollections","collectionHero"]},{"name":"collectionCta","label":"CTA","fields":[{"type":"string","name":"ctaEyebrow","label":"Айброу","namespace":["pageCollections","collectionCta","ctaEyebrow"],"searchable":true,"uid":false},{"type":"string","name":"ctaHeading","label":"Заголовок","ui":{"component":"textarea"},"namespace":["pageCollections","collectionCta","ctaHeading"],"searchable":true,"uid":false},{"type":"string","name":"ctaDesc","label":"Описание","ui":{"component":"textarea"},"namespace":["pageCollections","collectionCta","ctaDesc"],"searchable":true,"uid":false},{"type":"string","name":"ctaButton","label":"Кнопка","namespace":["pageCollections","collectionCta","ctaButton"],"searchable":true,"uid":false}],"namespace":["pageCollections","collectionCta"]}],"namespace":["pageCollections"]},{"name":"stores","label":"Магазины","path":"content/stores","format":"json","ui":{},"templates":[{"name":"storesHero","label":"Hero","fields":[{"type":"string","name":"heroEyebrow","label":"Айброу","namespace":["stores","storesHero","heroEyebrow"],"searchable":true,"uid":false},{"type":"string","name":"heroHeading","label":"Заголовок","ui":{"component":"textarea"},"namespace":["stores","storesHero","heroHeading"],"searchable":true,"uid":false},{"type":"string","name":"heroDesc","label":"Описание","namespace":["stores","storesHero","heroDesc"],"searchable":true,"uid":false}],"namespace":["stores","storesHero"]},{"name":"storesList","label":"Магазины (список)","fields":[{"type":"string","name":"storesEyebrow","label":"Айброу","namespace":["stores","storesList","storesEyebrow"],"searchable":true,"uid":false},{"type":"string","name":"storesDesc","label":"Описание","namespace":["stores","storesList","storesDesc"],"searchable":true,"uid":false},{"type":"string","name":"storesHeading","label":"Заголовок","ui":{"component":"textarea"},"namespace":["stores","storesList","storesHeading"],"searchable":true,"uid":false}],"namespace":["stores","storesList"]},{"name":"storesCta","label":"CTA","fields":[{"type":"string","name":"ctaHeading","label":"Заголовок","ui":{"component":"textarea"},"namespace":["stores","storesCta","ctaHeading"],"searchable":true,"uid":false},{"type":"string","name":"ctaDesc","label":"Описание","namespace":["stores","storesCta","ctaDesc"],"searchable":true,"uid":false},{"type":"string","name":"ctaButton","label":"Кнопка","namespace":["stores","storesCta","ctaButton"],"searchable":true,"uid":false}],"namespace":["stores","storesCta"]}],"namespace":["stores"]}],"config":{"media":{"tina":{"publicFolder":"public","mediaRoot":"uploads"}}}}